optimobo/__init__.py
optimobo/problem.py
optimobo/result.py
optimobo/scalarisations.py
optimobo/util_functions.py
optimobo/algorithms/__init__.py
optimobo/algorithms/cparego.py
optimobo/algorithms/emo.py
optimobo/algorithms/keep.py
optimobo/algorithms/optimisers.py
optimobo/algorithms/parego.py
optimobo/algorithms/turbo.py
optimobo-0.2.1.dist-info/LICENSE
optimobo-0.2.1.dist-info/METADATA
optimobo-0.2.1.dist-info/WHEEL
optimobo-0.2.1.dist-info/top_level.txt
optimobo-0.2.1.dist-info/RECORD
