Metadata-Version: 2.1
Name: optimobo
Version: 0.2.1
Summary: Solve multi-objective problems using Bayesian optimisation.
Author: aje220
Author-email: alexjacevans@gmail.com
License: MIT
License-File: LICENSE
Requires-Dist: numpy <=1.23.5
Requires-Dist: pymoo >=0.6.0
Requires-Dist: pygmo >=2.0.0
Requires-Dist: scipy >=1.9.0
Requires-Dist: gpy >=1.10.0
